setup.cfg
setup.py
./__init__.py
./carrier.py
./carrier.xml
./log.py
./party.py
./party.xml
./sale.py
./sale.xml
./shipment.py
./shipment.xml
./tryton.cfg
./locale/de_DE.po
./tests/__init__.py
./tests/test_party.py
./tests/test_shipping.py
./tests/test_views_depends.py
./view/address_form.xml
./view/address_suggestion_form.xml
./view/address_validation_end_form.xml
./view/carrier_configuration_form.xml
./view/carrier_form.xml
./view/generate_shipping_label_message_view_form.xml
./view/generate_shipping_label_wizard_start_view_form.xml
./view/no_module_form.xml
./view/package_form.xml
./view/sale_view_form.xml
./view/shipment_out_form.xml
./view/shipment_view_form.xml
openlabs_shipping.egg-info/PKG-INFO
openlabs_shipping.egg-info/SOURCES.txt
openlabs_shipping.egg-info/dependency_links.txt
openlabs_shipping.egg-info/entry_points.txt
openlabs_shipping.egg-info/not-zip-safe
openlabs_shipping.egg-info/requires.txt
openlabs_shipping.egg-info/top_level.txt